{"name":"Simple Audio Player","tagline":"Simple-Audio-Player is a lightweight JavaScript library which is implemented as a jQuery plugin and based on flash and soundmanager2.","body":"# Simple-Audio-Player\r\n\r\nSimple-Audio-Player is a lightweight JavaScript library which is implemented as a jQuery plugin and based on flash and soundmanager2.\r\n\r\n## Quick Start\r\n\r\n### Steps\r\n\r\n1. Clone the repository\r\n2. Place the content to the root\r\n3. Go to /example/index.html\r\n\r\n### Notices\r\n\r\n1. It is necessary to have a web server, you cannot open it statically\r\n2. Change path to swf directory in player.js if it is necessary\r\n\r\n![screen](https://raw.github.com/speranskydanil/Simple-Audio-Player/master/screen.png)\r\n\r\n**Author (Speransky Danil):**\r\n[Personal Page](http://dsperansky.info) |\r\n[LinkedIn](http://ru.linkedin.com/in/speranskydanil/en) |\r\n[GitHub](https://github.com/speranskydanil?tab=repositories) |\r\n[StackOverflow](http://stackoverflow.com/users/1550807/speransky-danil)\r\n","google":"UA-48799405-1","note":"Don't delete this file! It's used internally to help with page regeneration."}